{
    "id": 1,
    "name": "Angular Quiz",
    "description": "Angular Quiz ()",
    "questions": [
        {
            "id": 1010,
            "name": "What is Angular?",
            "questionTypeId": 1,
            "options": [
                {
                    "id": 1055,
                    "questionId": 1010,
                    "name": "A Framework",
                    "isAnswer": true
                },
                {
                    "id": 1056,
                    "questionId": 1010,
                    "name": "A Language",
                    "isAnswer": false
                },
                {
                    "id": 1057,
                    "questionId": 1010,
                    "name": "A type of fish",
                    "isAnswer": false
                },
                {
                    "id": 1058,
                    "questionId": 1010,
                    "name": "A design pattern",
                    "isAnswer": false
                }
            ],
            "questionType": {
                "id": 1,
                "name": "Multiple Choice",
                "isActive": true
            }
        },
        {
            "id": 1011,
            "name": "How do you use interpolation??",
            "questionTypeId": 1,
            "options": [
                {
                    "id": 1055,
                    "questionId": 1010,
                    "name": "{{}}",
                    "isAnswer": true
                },
                {
                    "id": 1057,
                    "questionId": 1010,
                    "name": "()",
                    "isAnswer": false
                },
                {
                    "id": 1056,
                    "questionId": 1010,
                    "name": "[]",
                    "isAnswer": false
                },
                {
                    "id": 1058,
                    "questionId": 1010,
                    "name": "[()]",
                    "isAnswer": false
                }
            ],
            "questionType": {
                "id": 1,
                "name": "Multiple Choice",
                "isActive": true
            }
        },
        {
            "id": 1012,
            "name": "How do you use two way binding?",
            "questionTypeId": 1,
            "options": [
                {
                    "id": 1055,
                    "questionId": 1010,
                    "name": "{{}}",
                    "isAnswer": false
                },
                {
                    "id": 1057,
                    "questionId": 1010,
                    "name": "()",
                    "isAnswer": false
                },
                {
                    "id": 1056,
                    "questionId": 1010,
                    "name": "[]",
                    "isAnswer": false
                },
                {
                    "id": 1058,
                    "questionId": 1010,
                    "name": "[()]",
                    "isAnswer": true
                }
            ],
            "questionType": {
                "id": 1,
                "name": "Multiple Choice",
                "isActive": true
            }
        },
        {
            "id": 1013,
            "name": "What is the purpose of binding??",
            "questionTypeId": 1,
            "options": [
                {
                    "id": 1055,
                    "questionId": 1010,
                    "name": "Connect components to the DOM",
                    "isAnswer": true
                },
                {
                    "id": 1057,
                    "questionId": 1010,
                    "name": "Connect modules to components",
                    "isAnswer": false
                },
                {
                    "id": 1056,
                    "questionId": 1010,
                    "name": "Create services",
                    "isAnswer": false
                },
                {
                    "id": 1058,
                    "questionId": 1010,
                    "name": "To do something",
                    "isAnswer": false
                }
            ],
            "questionType": {
                "id": 1,
                "name": "Multiple Choice",
                "isActive": true
            }
        },
        {
            "id": 1014,
            "name": "What are some main concepts of Angular?",
            "questionTypeId": 1,
            "options": [
                {
                    "id": 1055,
                    "questionId": 1010,
                    "name": "Modules",
                    "isAnswer": false
                },
                {
                    "id": 1057,
                    "questionId": 1010,
                    "name": "Components",
                    "isAnswer": false
                },
                {
                    "id": 1056,
                    "questionId": 1010,
                    "name": "Directives",
                    "isAnswer": false
                },
                {
                    "id": 1058,
                    "questionId": 1010,
                    "name": "All are main concepts",
                    "isAnswer": true
                }
            ],
            "questionType": {
                "id": 1,
                "name": "Multiple Choice",
                "isActive": true
            }
        },
        {
            "id": 1015,
            "name": "What guard interface determines whether to allow loading components?",
            "questionTypeId": 1,
            "options": [
                {
                    "id": 1055,
                    "questionId": 1010,
                    "name": "HttpClient",
                    "isAnswer": false
                },
                {
                    "id": 1057,
                    "questionId": 1010,
                    "name": "FormsModule",
                    "isAnswer": false
                },
                {
                    "id": 1056,
                    "questionId": 1010,
                    "name": "CanActivate",
                    "isAnswer": true
                },
                {
                    "id": 1058,
                    "questionId": 1010,
                    "name": "NgModule",
                    "isAnswer": false
                }
            ],
            "questionType": {
                "id": 1,
                "name": "Multiple Choice",
                "isActive": true
            }
        },
        {
            "id": 1016,
            "name": "How do you create a component in terminal?",
            "questionTypeId": 1,
            "options": [
                {
                    "id": 1055,
                    "questionId": 1010,
                    "name": "ng serve",
                    "isAnswer": false
                },
                {
                    "id": 1056,
                    "questionId": 1010,
                    "name": "ng g c <name>",
                    "isAnswer": true
                },
                {
                    "id": 1057,
                    "questionId": 1010,
                    "name": "ng g s <name>",
                    "isAnswer": false
                },
                {
                    "id": 1058,
                    "questionId": 1010,
                    "name": "ng serve <name>",
                    "isAnswer": false
                }
            ],
            "questionType": {
                "id": 1,
                "name": "Multiple Choice",
                "isActive": true
            }
        },
        {
            "id": 1017,
            "name": "What module allows for linking pages?",
            "questionTypeId": 1,
            "options": [
                {
                    "id": 1055,
                    "questionId": 1010,
                    "name": "HttpClient",
                    "isAnswer": false
                },
                {
                    "id": 1056,
                    "questionId": 1010,
                    "name": "Router",
                    "isAnswer": true
                },
                {
                    "id": 1057,
                    "questionId": 1010,
                    "name": "Forms",
                    "isAnswer": false
                },
                {
                    "id": 1058,
                    "questionId": 1010,
                    "name": "None",
                    "isAnswer": false
                }
            ],
            "questionType": {
                "id": 1,
                "name": "Multiple Choice",
                "isActive": true
            }
        },
        {
            "id": 1018,
            "name": "What are compenents?",
            "questionTypeId": 1,
            "options": [
                {
                    "id": 1055,
                    "questionId": 1010,
                    "name": "A type of form",
                    "isAnswer": false
                },
                {
                    "id": 1057,
                    "questionId": 1010,
                    "name": "A data type",
                    "isAnswer": false
                },
                {
                    "id": 1056,
                    "questionId": 1010,
                    "name": "The building blocks of Angular",
                    "isAnswer": true
                },
                {
                    "id": 1058,
                    "questionId": 1010,
                    "name": "An statement",
                    "isAnswer": false
                }
            ],
            "questionType": {
                "id": 1,
                "name": "Multiple Choice",
                "isActive": true
            }
        },
        {
            "id": 1019,
            "name": "You can pass data from a parent component to a child component using...",
            "questionTypeId": 1,
            "options": [
                {
                    "id": 1055,
                    "questionId": 1010,
                    "name": "@Input",
                    "isAnswer": true
                },
                {
                    "id": 1056,
                    "questionId": 1010,
                    "name": "@Output",
                    "isAnswer": false
                },
                {
                    "id": 1057,
                    "questionId": 1010,
                    "name": "Input",
                    "isAnswer": false
                },
                {
                    "id": 1058,
                    "questionId": 1010,
                    "name": "Output",
                    "isAnswer": false
                }
            ],
            "questionType": {
                "id": 1,
                "name": "Multiple Choice",
                "isActive": true
            }
        }
    ]
}